otel_extensions_pytest/__init__.py
otel_extensions_pytest/py.typed
otel_extensions_pytest-0.2.1.dist-info/LICENSE
otel_extensions_pytest-0.2.1.dist-info/METADATA
otel_extensions_pytest-0.2.1.dist-info/WHEEL
otel_extensions_pytest-0.2.1.dist-info/entry_points.txt
otel_extensions_pytest-0.2.1.dist-info/top_level.txt
otel_extensions_pytest-0.2.1.dist-info/zip-safe
otel_extensions_pytest-0.2.1.dist-info/RECORD
